speconed/__init__.py
speconed/speconed.py
speconed/data/__init__.py
speconed/data/example_spectra/J030341.04-002321.8_0.fits
speconed/data/example_spectra/J2125-1719_NIR.fits
speconed/data/example_spectra/J2125-1719_OPT_A.fits
speconed/data/example_spectra/J2125-1719_OPT_B.fits
speconed/data/example_spectra/J2125-1719_composite.hdf
speconed/data/example_spectra/__init__.py
speconed/data/passbands/2MASS-H.dat
speconed/data/passbands/2MASS-J.dat
speconed/data/passbands/2MASS-Ks.dat
speconed/data/passbands/CAHA_Omega2000-J.dat
speconed/data/passbands/DECAM-g.dat
speconed/data/passbands/DECAM-r.dat
speconed/data/passbands/DECAM-z.dat
speconed/data/passbands/FOURSTAR-J.dat
speconed/data/passbands/FOURSTAR-Ks.dat
speconed/data/passbands/HSC-g.dat
speconed/data/passbands/HSC-i.dat
speconed/data/passbands/HSC-r.dat
speconed/data/passbands/HSC-y.dat
speconed/data/passbands/HSC-z.dat
speconed/data/passbands/LCO_RetroCam-J.dat
speconed/data/passbands/LSST-g.dat
speconed/data/passbands/LSST-i.dat
speconed/data/passbands/LSST-r.dat
speconed/data/passbands/LSST-u.dat
speconed/data/passbands/LSST-y.dat
speconed/data/passbands/LSST-z.dat
speconed/data/passbands/LaSilla_GROND-H.dat
speconed/data/passbands/LaSilla_GROND-J.dat
speconed/data/passbands/LaSilla_GROND-K.dat
speconed/data/passbands/LaSilla_SOFI-H.dat
speconed/data/passbands/LaSilla_SOFI-J.dat
speconed/data/passbands/LaSilla_SOFI-Js.dat
speconed/data/passbands/LaSilla_SOFI-Ks.dat
speconed/data/passbands/PS1-g.dat
speconed/data/passbands/PS1-i.dat
speconed/data/passbands/PS1-r.dat
speconed/data/passbands/PS1-y.dat
speconed/data/passbands/PS1-z.dat
speconed/data/passbands/Paranal_VISTA-H.dat
speconed/data/passbands/Paranal_VISTA-J.dat
speconed/data/passbands/Paranal_VISTA-Ks.dat
speconed/data/passbands/Paranal_VISTA-Y.dat
speconed/data/passbands/Paranal_VISTA-Z.dat
speconed/data/passbands/README.txt
speconed/data/passbands/SDSS-g.dat
speconed/data/passbands/SDSS-i.dat
speconed/data/passbands/SDSS-r.dat
speconed-1.0.1.dist-info/LICENSE
speconed-1.0.1.dist-info/METADATA
speconed-1.0.1.dist-info/WHEEL
speconed-1.0.1.dist-info/top_level.txt
speconed-1.0.1.dist-info/RECORD
