Metadata-Version: 2.1
Name: speconed
Version: 1.0.1
Summary: A lightweight package for the manipulation of 1-D astronomical specta
Home-page: https://github.com/jtschindler/speconed
Author: Jan-Torge Schindler
Author-email: schindler@strw.leidenuniv.nl
License: BSD-3-Clause
Project-URL: Bug Tracker, https://github.com/jtschindler/speconed/issues
Keywords: spectroscopy,astronomy,science,python
Classifier: Development Status :: 4 - Beta
Classifier: Intended Audience :: Science/Research
Classifier: License :: OSI Approved :: BSD License
Classifier: Operating System :: OS Independent
Classifier: Programming Language :: Python :: 3.9
Classifier: Topic :: Scientific/Engineering :: Astronomy
Classifier: Topic :: Scientific/Engineering :: Physics
Requires-Python: >=3.9
License-File: LICENSE
Requires-Dist: numpy
Requires-Dist: scipy
Requires-Dist: pandas
Requires-Dist: h5py
Requires-Dist: extinction
Requires-Dist: spectres
Requires-Dist: astropy
Requires-Dist: matplotlib
Requires-Dist: tables
Requires-Dist: notebook
Requires-Dist: nbsphinx
Requires-Dist: nbsphinx-link
Requires-Dist: sphinx-rtd-theme
